aineko_style/__init__.py
aineko_style/checker.py
aineko_style-0.0.2.dist-info/LICENSE
aineko_style-0.0.2.dist-info/METADATA
aineko_style-0.0.2.dist-info/WHEEL
aineko_style-0.0.2.dist-info/RECORD
