Metadata-Version: 2.1
Name: aineko_style
Version: 0.0.2
Summary: Custom pylint rules for aineko-dev codebases.
Home-page: https://github.com/aineko-dev/aineko_style
License: Apache-2.0
Author: Aineko Engineering
Author-email: engineering@aineko.dev
Requires-Python: >=3.8,<3.13
Classifier: Development Status :: 3 - Alpha
Classifier: Environment :: Plugins
Classifier: Intended Audience :: Developers
Classifier: License :: OSI Approved :: Apache Software License
Classifier: Natural Language :: English
Classifier: Programming Language :: Python :: 3
Classifier: Programming Language :: Python :: 3.8
Classifier: Programming Language :: Python :: 3.9
Classifier: Programming Language :: Python :: 3.10
Classifier: Programming Language :: Python :: 3.11
Classifier: Typing :: Typed
Requires-Dist: pylint (>=2.17.5,<3.0.0)
Project-URL: Repository, https://github.com/aineko-dev/aineko_style
